{"assets":[],"layers":[{"ddd":0,"ind":0,"ty":4,"nm":"message_1","parent":10,"ks":{"o":{"k":100},"r":{"k":0},"p":{"k":[118,-106.5,0]},"a":{"k":[75,-124.5,0]},"s":{"k":[{"i":{"x":[0.25,0.25,0.25],"y":[1,1,0.25]},"o":{"x":[0.333,0.333,0.333],"y":[0,0,0.333]},"n":["0p25_1_0p333_0","0p25_1_0p333_0","0p25_0p25_0p333_0p333"],"t":31,"s":[0,0,100],"e":[100,100,100]},{"t":64}]}},"ao":0,"shapes":[{"ty":"gr","it":[{"ty":"rc","d":1,"s":{"k":[132,30]},"p":{"k":[0,0]},"r":{"k":1},"nm":"Rectangle Path 1","mn":"ADBE Vector Shape - Rect"},{"ty":"st","c":{"k":[0.15,0.58,0.04,1]},"o":{"k":100},"w":{"k":0},"lc":1,"lj":1,"ml":4,"nm":"Stroke 1","mn":"ADBE Vector Graphic - Stroke"},{"ty":"fl","c":{"k":[0.59,0.82,0.35,1]},"o":{"k":100},"nm":"Fill 1","mn":"ADBE Vector Graphic - Fill"},{"ty":"tr","p":{"k":[9,-139.5],"ix":2},"a":{"k":[0,0],"ix":1},"s":{"k":[100,100],"ix":3},"r":{"k":0,"ix":6},"o":{"k":100,"ix":7},"sk":{"k":0,"ix":4},"sa":{"k":0,"ix":5},"nm":"Transform"}],"nm":"Rectangle 1","np":3,"mn":"ADBE Vector Group"}],"ip":31,"op":121,"st":31,"bm":0,"sr":1},{"ddd":0,"ind":1,"ty":4,"nm":"message_2","parent":10,"ks":{"o":{"k":100},"r":{"k":0},"p":{"k":[-32,-61.5,0]},"a":{"k":[-57,-124.5,0]},"s":{"k":[{"i":{"x":[0.25,0.25,0.25],"y":[1,1,0.25]},"o":{"x":[0.333,0.333,0.333],"y":[0,0,0.333]},"n":["0p25_1_0p333_0","0p25_1_0p333_0","0p25_0p25_0p333_0p333"],"t":35,"s":[0,0,100],"e":[78,98,100]},{"t":68}]}},"ao":0,"shapes":[{"ty":"gr","it":[{"ty":"rc","d":1,"s":{"k":[132,30]},"p":{"k":[0,0]},"r":{"k":1},"nm":"Rectangle Path 1","mn":"ADBE Vector Shape - Rect"},{"ty":"st","c":{"k":[0.15,0.58,0.04,1]},"o":{"k":100},"w":{"k":0},"lc":1,"lj":1,"ml":4,"nm":"Stroke 1","mn":"ADBE Vector Graphic - Stroke"},{"ty":"fl","c":{"k":[0.28,0.69,0.17,1]},"o":{"k":100},"nm":"Fill 1","mn":"ADBE Vector Graphic - Fill"},{"ty":"tr","p":{"k":[9,-139.5],"ix":2},"a":{"k":[0,0],"ix":1},"s":{"k":[100,100],"ix":3},"r":{"k":0,"ix":6},"o":{"k":100,"ix":7},"sk":{"k":0,"ix":4},"sa":{"k":0,"ix":5},"nm":"Transform"}],"nm":"Rectangle 1","np":3,"mn":"ADBE Vector Group"}],"ip":35,"op":121,"st":35,"bm":0,"sr":1},{"ddd":0,"ind":2,"ty":4,"nm":"message_3","parent":10,"ks":{"o":{"k":100},"r":{"k":0},"p":{"k":[-32,-33,0]},"a":{"k":[-57,-124.5,0]},"s":{"k":[{"i":{"x":[0.25,0.25,0.25],"y":[1,1,0.25]},"o":{"x":[0.333,0.333,0.333],"y":[0,0,0.333]},"n":["0p25_1_0p333_0","0p25_1_0p333_0","0p25_0p25_0p333_0p333"],"t":39,"s":[0,0,100],"e":[86,48,100]},{"t":72}]}},"ao":0,"shapes":[{"ty":"gr","it":[{"ty":"rc","d":1,"s":{"k":[132,30]},"p":{"k":[0,0]},"r":{"k":1},"nm":"Rectangle Path 1","mn":"ADBE Vector Shape - Rect"},{"ty":"st","c":{"k":[0.15,0.58,0.04,1]},"o":{"k":100},"w":{"k":0},"lc":1,"lj":1,"ml":4,"nm":"Stroke 1","mn":"ADBE Vector Graphic - Stroke"},{"ty":"fl","c":{"k":[0.28,0.69,0.17,1]},"o":{"k":100},"nm":"Fill 1","mn":"ADBE Vector Graphic - Fill"},{"ty":"tr","p":{"k":[9,-139.5],"ix":2},"a":{"k":[0,0],"ix":1},"s":{"k":[100,100],"ix":3},"r":{"k":0,"ix":6},"o":{"k":100,"ix":7},"sk":{"k":0,"ix":4},"sa":{"k":0,"ix":5},"nm":"Transform"}],"nm":"Rectangle 1","np":3,"mn":"ADBE Vector Group"}],"ip":39,"op":121,"st":39,"bm":0,"sr":1},{"ddd":0,"ind":3,"ty":4,"nm":"message_4","parent":10,"ks":{"o":{"k":100},"r":{"k":0},"p":{"k":[115,8,0]},"a":{"k":[75,-124.5,0]},"s":{"k":[{"i":{"x":[0.25,0.25,0.25],"y":[1,1,0.25]},"o":{"x":[0.333,0.333,0.333],"y":[0,0,0.333]},"n":["0p25_1_0p333_0","0p25_1_0p333_0","0p25_0p25_0p333_0p333"],"t":43,"s":[0,0,100],"e":[82,87,100]},{"t":76}]}},"ao":0,"shapes":[{"ty":"gr","it":[{"ty":"rc","d":1,"s":{"k":[132,30]},"p":{"k":[0,0]},"r":{"k":1},"nm":"Rectangle Path 1","mn":"ADBE Vector Shape - Rect"},{"ty":"st","c":{"k":[0.15,0.58,0.04,1]},"o":{"k":100},"w":{"k":0},"lc":1,"lj":1,"ml":4,"nm":"Stroke 1","mn":"ADBE Vector Graphic - Stroke"},{"ty":"fl","c":{"k":[0.59,0.82,0.35,1]},"o":{"k":100},"nm":"Fill 1","mn":"ADBE Vector Graphic - Fill"},{"ty":"tr","p":{"k":[9,-139.5],"ix":2},"a":{"k":[0,0],"ix":1},"s":{"k":[100,100],"ix":3},"r":{"k":0,"ix":6},"o":{"k":100,"ix":7},"sk":{"k":0,"ix":4},"sa":{"k":0,"ix":5},"nm":"Transform"}],"nm":"Rectangle 1","np":3,"mn":"ADBE Vector Group"}],"ip":43,"op":121,"st":43,"bm":0,"sr":1},{"ddd":0,"ind":4,"ty":4,"nm":"message_5","parent":10,"ks":{"o":{"k":100},"r":{"k":0},"p":{"k":[-32,37,0]},"a":{"k":[-57,-124.5,0]},"s":{"k":[{"i":{"x":[0.25,0.25,0.25],"y":[1,1,0.25]},"o":{"x":[0.333,0.333,0.333],"y":[0,0,0.333]},"n":["0p25_1_0p333_0","0p25_1_0p333_0","0p25_0p25_0p333_0p333"],"t":47,"s":[0,0,100],"e":[52,48,100]},{"t":80}]}},"ao":0,"shapes":[{"ty":"gr","it":[{"ty":"rc","d":1,"s":{"k":[132,30]},"p":{"k":[0,0]},"r":{"k":1},"nm":"Rectangle Path 1","mn":"ADBE Vector Shape - Rect"},{"ty":"st","c":{"k":[0.15,0.58,0.04,1]},"o":{"k":100},"w":{"k":0},"lc":1,"lj":1,"ml":4,"nm":"Stroke 1","mn":"ADBE Vector Graphic - Stroke"},{"ty":"fl","c":{"k":[0.28,0.69,0.17,1]},"o":{"k":100},"nm":"Fill 1","mn":"ADBE Vector Graphic - Fill"},{"ty":"tr","p":{"k":[9,-139.5],"ix":2},"a":{"k":[0,0],"ix":1},"s":{"k":[100,100],"ix":3},"r":{"k":0,"ix":6},"o":{"k":100,"ix":7},"sk":{"k":0,"ix":4},"sa":{"k":0,"ix":5},"nm":"Transform"}],"nm":"Rectangle 1","np":3,"mn":"ADBE Vector Group"}],"ip":47,"op":121,"st":47,"bm":0,"sr":1},{"ddd":0,"ind":5,"ty":4,"nm":"message_6","parent":10,"ks":{"o":{"k":100},"r":{"k":0},"p":{"k":[115,64,0]},"a":{"k":[75,-124.5,0]},"s":{"k":[{"i":{"x":[0.25,0.25,0.25],"y":[1,1,0.25]},"o":{"x":[0.333,0.333,0.333],"y":[0,0,0.333]},"n":["0p25_1_0p333_0","0p25_1_0p333_0","0p25_0p25_0p333_0p333"],"t":51,"s":[0,0,100],"e":[98,45,100]},{"t":84}]}},"ao":0,"shapes":[{"ty":"gr","it":[{"ty":"rc","d":1,"s":{"k":[132,30]},"p":{"k":[0,0]},"r":{"k":1},"nm":"Rectangle Path 1","mn":"ADBE Vector Shape - Rect"},{"ty":"st","c":{"k":[0.15,0.58,0.04,1]},"o":{"k":100},"w":{"k":0},"lc":1,"lj":1,"ml":4,"nm":"Stroke 1","mn":"ADBE Vector Graphic - Stroke"},{"ty":"fl","c":{"k":[0.59,0.82,0.35,1]},"o":{"k":100},"nm":"Fill 1","mn":"ADBE Vector Graphic - Fill"},{"ty":"tr","p":{"k":[9,-139.5],"ix":2},"a":{"k":[0,0],"ix":1},"s":{"k":[100,100],"ix":3},"r":{"k":0,"ix":6},"o":{"k":100,"ix":7},"sk":{"k":0,"ix":4},"sa":{"k":0,"ix":5},"nm":"Transform"}],"nm":"Rectangle 1","np":3,"mn":"ADBE Vector Group"}],"ip":51,"op":121,"st":51,"bm":0,"sr":1},{"ddd":0,"ind":6,"ty":4,"nm":"message_7","parent":10,"ks":{"o":{"k":100},"r":{"k":0},"p":{"k":[115,90,0]},"a":{"k":[75,-124.5,0]},"s":{"k":[{"i":{"x":[0.25,0.25,0.25],"y":[1,1,0.25]},"o":{"x":[0.333,0.333,0.333],"y":[0,0,0.333]},"n":["0p25_1_0p333_0","0p25_1_0p333_0","0p25_0p25_0p333_0p333"],"t":55,"s":[0,0,100],"e":[75,45,100]},{"t":88}]}},"ao":0,"shapes":[{"ty":"gr","it":[{"ty":"rc","d":1,"s":{"k":[132,30]},"p":{"k":[0,0]},"r":{"k":1},"nm":"Rectangle Path 1","mn":"ADBE Vector Shape - Rect"},{"ty":"st","c":{"k":[0.15,0.58,0.04,1]},"o":{"k":100},"w":{"k":0},"lc":1,"lj":1,"ml":4,"nm":"Stroke 1","mn":"ADBE Vector Graphic - Stroke"},{"ty":"fl","c":{"k":[0.59,0.82,0.35,1]},"o":{"k":100},"nm":"Fill 1","mn":"ADBE Vector Graphic - Fill"},{"ty":"tr","p":{"k":[9,-139.5],"ix":2},"a":{"k":[0,0],"ix":1},"s":{"k":[100,100],"ix":3},"r":{"k":0,"ix":6},"o":{"k":100,"ix":7},"sk":{"k":0,"ix":4},"sa":{"k":0,"ix":5},"nm":"Transform"}],"nm":"Rectangle 1","np":3,"mn":"ADBE Vector Group"}],"ip":55,"op":121,"st":55,"bm":0,"sr":1},{"ddd":0,"ind":7,"ty":4,"nm":"message_8","parent":10,"ks":{"o":{"k":100},"r":{"k":0},"p":{"k":[-32,118,0]},"a":{"k":[-57,-124.5,0]},"s":{"k":[{"i":{"x":[0.25,0.25,0.25],"y":[1,1,0.25]},"o":{"x":[0.333,0.333,0.333],"y":[0,0,0.333]},"n":["0p25_1_0p333_0","0p25_1_0p333_0","0p25_0p25_0p333_0p333"],"t":59,"s":[0,0,100],"e":[52,48,100]},{"t":92}]}},"ao":0,"shapes":[{"ty":"gr","it":[{"ty":"rc","d":1,"s":{"k":[132,30]},"p":{"k":[0,0]},"r":{"k":1},"nm":"Rectangle Path 1","mn":"ADBE Vector Shape - Rect"},{"ty":"st","c":{"k":[0.15,0.58,0.04,1]},"o":{"k":100},"w":{"k":0},"lc":1,"lj":1,"ml":4,"nm":"Stroke 1","mn":"ADBE Vector Graphic - Stroke"},{"ty":"fl","c":{"k":[0.28,0.69,0.17,1]},"o":{"k":100},"nm":"Fill 1","mn":"ADBE Vector Graphic - Fill"},{"ty":"tr","p":{"k":[9,-139.5],"ix":2},"a":{"k":[0,0],"ix":1},"s":{"k":[100,100],"ix":3},"r":{"k":0,"ix":6},"o":{"k":100,"ix":7},"sk":{"k":0,"ix":4},"sa":{"k":0,"ix":5},"nm":"Transform"}],"nm":"Rectangle 1","np":3,"mn":"ADBE Vector Group"}],"ip":59,"op":121,"st":59,"bm":0,"sr":1},{"ddd":0,"ind":8,"ty":4,"nm":"button","parent":10,"ks":{"o":{"k":100},"r":{"k":0},"p":{"k":[42,173,0]},"a":{"k":[-4.5,158.5,0]},"s":{"k":[100,100,100]}},"ao":0,"shapes":[{"ty":"gr","it":[{"ty":"rc","d":1,"s":{"k":[47,47]},"p":{"k":[0,0]},"r":{"k":0},"nm":"Rectangle Path 1","mn":"ADBE Vector Shape - Rect"},{"ty":"st","c":{"k":[0.15,0.58,0.04,1]},"o":{"k":100},"w":{"k":[{"i":{"x":[0.1],"y":[1]},"o":{"x":[0.333],"y":[0]},"n":["0p1_1_0p333_0"],"t":37,"s":[0],"e":[8]},{"t":85}]},"lc":1,"lj":1,"ml":4,"nm":"Stroke 1","mn":"ADBE Vector Graphic - Stroke"},{"ty":"tr","p":{"k":[-4.5,158.5],"ix":2},"a":{"k":[0,0],"ix":1},"s":{"k":[100,100],"ix":3},"r":{"k":0,"ix":6},"o":{"k":100,"ix":7},"sk":{"k":0,"ix":4},"sa":{"k":0,"ix":5},"nm":"Transform"}],"nm":"Rectangle 1","np":3,"mn":"ADBE Vector Group"}],"ip":5,"op":121,"st":5,"bm":0,"sr":1},{"ddd":0,"ind":9,"ty":4,"nm":"screen","parent":10,"ks":{"o":{"k":100},"r":{"k":0},"p":{"k":[42,-9,0]},"a":{"k":[42,-1,0]},"s":{"k":[{"i":{"x":[0.25,0.25,0.25],"y":[1,1,0.25]},"o":{"x":[0.333,0.333,0.333],"y":[0,0,0.333]},"n":["0p25_1_0p333_0","0p25_1_0p333_0","0p25_0p25_0p333_0p333"],"t":6,"s":[0,0,100],"e":[100,100,100]},{"t":56}]}},"ao":0,"shapes":[{"ty":"gr","it":[{"ty":"rc","d":1,"s":{"k":[182.888,291]},"p":{"k":[0,0]},"r":{"k":0},"nm":"Rectangle Path 1","mn":"ADBE Vector Shape - Rect"},{"ty":"st","c":{"k":[0.25,0.25,0.25,1]},"o":{"k":100},"w":{"k":0},"lc":1,"lj":1,"ml":4,"nm":"Stroke 1","mn":"ADBE Vector Graphic - Stroke"},{"ty":"fl","c":{"k":[0.95,1,0.84,1]},"o":{"k":100},"nm":"Fill 1","mn":"ADBE Vector Graphic - Fill"},{"ty":"tr","p":{"k":[42,-1],"ix":2},"a":{"k":[0,0],"ix":1},"s":{"k":[100,100],"ix":3},"r":{"k":0,"ix":6},"o":{"k":100,"ix":7},"sk":{"k":0,"ix":4},"sa":{"k":0,"ix":5},"nm":"Transform"}],"nm":"Rectangle 1","np":3,"mn":"ADBE Vector Group"}],"ip":6,"op":121,"st":6,"bm":0,"sr":1},{"ddd":0,"ind":10,"ty":4,"nm":"body","ks":{"o":{"k":100},"r":{"k":0},"p":{"k":[400,300,0]},"a":{"k":[42,20,0]},"s":{"k":[{"i":{"x":[0.25,0.25,0.25],"y":[1,1,0.25]},"o":{"x":[0.333,0.333,0.333],"y":[0,0,0.333]},"n":["0p25_1_0p333_0","0p25_1_0p333_0","0p25_0p25_0p333_0p333"],"t":5,"s":[0,0,100],"e":[100,100,100]},{"t":55}]}},"ao":0,"shapes":[{"ty":"gr","it":[{"ty":"rc","d":1,"s":{"k":[231.303,394]},"p":{"k":[0,0]},"r":{"k":0},"nm":"Rectangle Path 1","mn":"ADBE Vector Shape - Rect"},{"ty":"st","c":{"k":[0.15,0.58,0.04,1]},"o":{"k":100},"w":{"k":[{"i":{"x":[0.1],"y":[1]},"o":{"x":[0.333],"y":[0]},"n":["0p1_1_0p333_0"],"t":37,"s":[0],"e":[14]},{"i":{"x":[0.833],"y":[1]},"o":{"x":[0.9],"y":[0]},"n":["0p833_1_0p9_0"],"t":85,"s":[14],"e":[13]},{"t":98}]},"lc":1,"lj":1,"ml":4,"nm":"Stroke 1","mn":"ADBE Vector Graphic - Stroke"},{"ty":"fl","c":{"k":[0.53,0.82,0.16,1]},"o":{"k":100},"nm":"Fill 1","mn":"ADBE Vector Graphic - Fill"},{"ty":"tr","p":{"k":[42,20],"ix":2},"a":{"k":[0,0],"ix":1},"s":{"k":[100,100],"ix":3},"r":{"k":0,"ix":6},"o":{"k":100,"ix":7},"sk":{"k":0,"ix":4},"sa":{"k":0,"ix":5},"nm":"Transform"}],"nm":"Rectangle 1","np":3,"mn":"ADBE Vector Group"}],"ip":5,"op":121,"st":5,"bm":0,"sr":1},{"ddd":0,"ind":11,"ty":4,"nm":"background","ks":{"o":{"k":100},"r":{"k":0},"p":{"k":[400,300,0]},"a":{"k":[0,0,0]},"s":{"k":[100,100,100]}},"ao":0,"shapes":[{"ty":"gr","it":[{"ty":"rc","d":1,"s":{"k":[800,600]},"p":{"k":[0,0]},"r":{"k":0},"nm":"Rectangle Path 1","mn":"ADBE Vector Shape - Rect"},{"ty":"st","c":{"k":[1,1,1,1]},"o":{"k":100},"w":{"k":0},"lc":1,"lj":1,"ml":4,"nm":"Stroke 1","mn":"ADBE Vector Graphic - Stroke"},{"ty":"fl","c":{"k":[1,1,1,1]},"o":{"k":100},"nm":"Fill 1","mn":"ADBE Vector Graphic - Fill"},{"ty":"tr","p":{"k":[0,0],"ix":2},"a":{"k":[0,0],"ix":1},"s":{"k":[100,100],"ix":3},"r":{"k":0,"ix":6},"o":{"k":100,"ix":7},"sk":{"k":0,"ix":4},"sa":{"k":0,"ix":5},"nm":"Transform"}],"nm":"Rectangle 1","np":3,"mn":"ADBE Vector Group"}],"ip":0,"op":121,"st":0,"bm":0,"sr":1}],"v":"4.5.4","ddd":0,"ip":0,"op":121,"fr":30,"w":800,"h":600}